LICENSE.txt
MANIFEST.in
README.md
requirements.txt
setup.py
rocketman/__init__.py
rocketman/capsule.py
rocketman/common.py
rocketman/company.py
rocketman/core.py
rocketman/crewmember.py
rocketman/dragon.py
rocketman/errors.py
rocketman/history.py
rocketman/http.py
rocketman/landingpad.py
rocketman/launch.py
rocketman/launchpad.py
rocketman/payload.py
rocketman/roadster.py
rocketman/rocket.py
rocketman/rocketman.py
rocketman/ship.py
rocketman/starlink.py
rocketman.egg-info/PKG-INFO
rocketman.egg-info/SOURCES.txt
rocketman.egg-info/dependency_links.txt
rocketman.egg-info/requires.txt
rocketman.egg-info/top_level.txt
rocketman/types/__init__.py
rocketman/types/capsule.py
rocketman/types/common.py
rocketman/types/company.py
rocketman/types/core.py
rocketman/types/crewmember.py
rocketman/types/dragon.py
rocketman/types/history.py
rocketman/types/landingpad.py
rocketman/types/launch.py
rocketman/types/launchpad.py
rocketman/types/payload.py
rocketman/types/roadster.py
rocketman/types/rocket.py
rocketman/types/ship.py
rocketman/types/starlink.py
rocketman/utils/__init__.py
rocketman/utils/objects.py